resourcepack/__init__.py
resourcepack/database.py
resourcepack/essentials.py
resourcepack/errors/__init__.py
resourcepack/errors/base.py
tests/__init__.py
tests/test_database.py
resourcepack-0.1.5.dist-info/LICENSE
resourcepack-0.1.5.dist-info/METADATA
resourcepack-0.1.5.dist-info/WHEEL
resourcepack-0.1.5.dist-info/top_level.txt
resourcepack-0.1.5.dist-info/RECORD
